cocanb/__init__.py
cocanb/cocanb_to_english.py
cocanb/diacritics.py
cocanb/english_to_cocanb.py
cocanb/quotes.py
cocanb/sentences.py
cocanb/spaces.py
cocanb-0.0.dist-info/METADATA
cocanb-0.0.dist-info/WHEEL
cocanb-0.0.dist-info/top_level.txt
cocanb-0.0.dist-info/RECORD
