Metadata-Version: 2.1
Name: cocanb
Version: 0.0
Summary: UNKNOWN
Home-page: UNKNOWN
Author: UNKNOWN
Author-email: UNKNOWN
License: UNKNOWN
Platform: UNKNOWN
Requires-Dist: importlib
Requires-Dist: numpy
Requires-Dist: unidecode
